brainwire/__init__.py
brainwire/decode.py
brainwire/encode.py
brainwire-0.1.8.dist-info/LICENSE
brainwire-0.1.8.dist-info/METADATA
brainwire-0.1.8.dist-info/WHEEL
brainwire-0.1.8.dist-info/top_level.txt
brainwire-0.1.8.dist-info/RECORD
