Metadata-Version: 2.1
Name: brainwire
Version: 0.1.8
Summary: Tools to losslessly compress and decompress raw neural data.
Author: Evan Woods
Maintainer: Evan Woods
License: MIT License
Project-URL: Homepage, https://github.com/efwoods/Neuralink-Compression-Challenge
Project-URL: Issues, https://github.com/efwoods/Neuralink-Compression-Challenge/issues
Requires-Python: >=3.10
License-File: LICENSE
Requires-Dist: numpy >=1.0
Requires-Dist: scipy
Requires-Dist: numpy
Requires-Dist: signal-processing-utilities >=0.1.8
